{
  "buildFiles": [
    "D:\\flutter_windows_3.7.3-stable\\flutter_windows_3.24.5-stable\\flutter\\packages\\flutter_tools\\gradle\\src\\main\\groovy\\CMakeLists.txt"
  ],
  "cleanCommandsComponents": [
    [
      "C:\\Users\\sw\\AppData\\Local\\Android\\sdk\\cmake\\3.22.1\\bin\\ninja.exe",
      "-C",
      "E:\\flutter-project 2\\flutter-project\\flutter_application\\android\\app\\.cxx\\RelWithDebInfo\\6x2x343a\\armeabi-v7a",
      "clean"
    ]
  ],
  "buildTargetsCommandComponents": [
    "C:\\Users\\sw\\AppData\\Local\\Android\\sdk\\cmake\\3.22.1\\bin\\ninja.exe",
    "-C",
    "E:\\flutter-project 2\\flutter-project\\flutter_application\\android\\app\\.cxx\\RelWithDebInfo\\6x2x343a\\armeabi-v7a",
    "{LIST_OF_TARGETS_TO_BUILD}"
  ],
  "libraries": {},
  "toolchains": {
    "toolchain": {
      "cCompilerExecutable": "C:\\Users\\sw\\AppData\\Local\\Android\\Sdk\\ndk\\26.3.11579264\\toolchains\\llvm\\prebuilt\\windows-x86_64\\bin\\clang.exe",
      "cppCompilerExecutable": "C:\\Users\\sw\\AppData\\Local\\Android\\Sdk\\ndk\\26.3.11579264\\toolchains\\llvm\\prebuilt\\windows-x86_64\\bin\\clang++.exe"
    }
  },
  "cFileExtensions": [],
  "cppFileExtensions": []
}